xemporal/__init__.py
xemporal/ext.abi3.so
xemporal/src/main.zig
xemporal/src/utils.zig
xemporal-0.1.3.dist-info/METADATA
xemporal-0.1.3.dist-info/WHEEL
xemporal-0.1.3.dist-info/RECORD
